<tv generator-info-name="youtube-live-epg" generator-info-url="https://github.com/dp247/YouTubeToM3U8">
  <channel id="DW.es">
    <display-name lang="en">DW Espa帽ol</display-name>
  </channel>
  <programme channel="DW.es" start="20250111200000 +0000" stop="20250111230000 +0000">
    <title lang="en"> DW Espa帽ol | En vivo</title>
    <desc lang="en">Noticias internacionales, informaci贸n econ贸mica y reportajes desde Alemania con objetividad para el mundo. En esta plataforma DW Espa帽ol ofrece tambi茅n progr...</desc>
    <icon src="https://i.ytimg.com/vi/Io5mt83nCcU/maxresdefault.jpg?v=66b20f97"/>
  </programme>
  <programme channel="DW.es" start="20250111230000 +0000" stop="20250112020000 +0000">
    <title lang="en"> DW Espa帽ol | En vivo</title>
    <desc lang="en">Noticias internacionales, informaci贸n econ贸mica y reportajes desde Alemania con objetividad para el mundo. En esta plataforma DW Espa帽ol ofrece tambi茅n progr...</desc>
    <icon src="https://i.ytimg.com/vi/Io5mt83nCcU/maxresdefault.jpg?v=66b20f97"/>
  </programme>
  <programme channel="DW.es" start="20250112020000 +0000" stop="20250112050000 +0000">
    <title lang="en"> DW Espa帽ol | En vivo</title>
    <desc lang="en">Noticias internacionales, informaci贸n econ贸mica y reportajes desde Alemania con objetividad para el mundo. En esta plataforma DW Espa帽ol ofrece tambi茅n progr...</desc>
    <icon src="https://i.ytimg.com/vi/Io5mt83nCcU/maxresdefault.jpg?v=66b20f97"/>
  </programme>
  <programme channel="DW.es" start="20250112050000 +0000" stop="20250112080000 +0000">
    <title lang="en"> DW Espa帽ol | En vivo</title>
    <desc lang="en">Noticias internacionales, informaci贸n econ贸mica y reportajes desde Alemania con objetividad para el mundo. En esta plataforma DW Espa帽ol ofrece tambi茅n progr...</desc>
    <icon src="https://i.ytimg.com/vi/Io5mt83nCcU/maxresdefault.jpg?v=66b20f97"/>
  </programme>
  <programme channel="DW.es" start="20250112080000 +0000" stop="20250112110000 +0000">
    <title lang="en"> DW Espa帽ol | En vivo</title>
    <desc lang="en">Noticias internacionales, informaci贸n econ贸mica y reportajes desde Alemania con objetividad para el mundo. En esta plataforma DW Espa帽ol ofrece tambi茅n progr...</desc>
    <icon src="https://i.ytimg.com/vi/Io5mt83nCcU/maxresdefault.jpg?v=66b20f97"/>
  </programme>
  <programme channel="DW.es" start="20250112110000 +0000" stop="20250112140000 +0000">
    <title lang="en"> DW Espa帽ol | En vivo</title>
    <desc lang="en">Noticias internacionales, informaci贸n econ贸mica y reportajes desde Alemania con objetividad para el mundo. En esta plataforma DW Espa帽ol ofrece tambi茅n progr...</desc>
    <icon src="https://i.ytimg.com/vi/Io5mt83nCcU/maxresdefault.jpg?v=66b20f97"/>
  </programme>
  <programme channel="DW.es" start="20250112140000 +0000" stop="20250112170000 +0000">
    <title lang="en"> DW Espa帽ol | En vivo</title>
    <desc lang="en">Noticias internacionales, informaci贸n econ贸mica y reportajes desde Alemania con objetividad para el mundo. En esta plataforma DW Espa帽ol ofrece tambi茅n progr...</desc>
    <icon src="https://i.ytimg.com/vi/Io5mt83nCcU/maxresdefault.jpg?v=66b20f97"/>
  </programme>
  <programme channel="DW.es" start="20250112170000 +0000" stop="20250112200000 +0000">
    <title lang="en"> DW Espa帽ol | En vivo</title>
    <desc lang="en">Noticias internacionales, informaci贸n econ贸mica y reportajes desde Alemania con objetividad para el mundo. En esta plataforma DW Espa帽ol ofrece tambi茅n progr...</desc>
    <icon src="https://i.ytimg.com/vi/Io5mt83nCcU/maxresdefault.jpg?v=66b20f97"/>
  </programme>
</tv>
